djangomail/__init__.py
djangomail/exceptions.py
djangomail/message.py
djangomail/backends/__init__.py
djangomail/backends/base.py
djangomail/backends/console.py
djangomail/backends/dummy.py
djangomail/backends/filebased.py
djangomail/backends/locmem.py
djangomail/backends/smtp.py
djangomail/conf/__init__.py
djangomail/conf/global_settings.py
djangomail/utils/__init__.py
djangomail/utils/encoding.py
djangomail/utils/functional.py
djangomail/utils/hashable.py
djangomail/utils/itercompat.py
djangomail/utils/module_loading.py
djangomail-0.8.dist-info/LICENSE
djangomail-0.8.dist-info/METADATA
djangomail-0.8.dist-info/WHEEL
djangomail-0.8.dist-info/top_level.txt
djangomail-0.8.dist-info/RECORD
