Metadata-Version: 2.1
Name: djangomail
Version: 0.8
Summary: A stand-alone mail module from django
Home-page: https://github.com/somenzz/djangomail
Author: somenzz
Author-email: somenzz@163.com
License: MIT
Keywords: python send email
Classifier: Development Status :: 3 - Alpha
Classifier: Intended Audience :: Developers
Classifier: License :: OSI Approved :: MIT License
Classifier: Operating System :: OS Independent
Classifier: Programming Language :: Python
Classifier: Programming Language :: Python :: 3
Classifier: Topic :: Software Development
Classifier: Topic :: Software Development :: Libraries :: Python Modules
Classifier: Topic :: Utilities
License-File: LICENSE
